QPrism/__init__.py
QPrism/Audio/DQM.py
QPrism/Audio/__init__.py
QPrism/Audio/audio_classification.py
QPrism/Audio/audio_length.py
QPrism/Audio/audio_rms.py
QPrism/Audio/audio_sample_rate.py
QPrism/Audio/helpers/audio_paths.py
QPrism/Audio/helpers/audio_to_array.py
QPrism/Audio/helpers/download.py
QPrism/Audio/helpers/to_dataframe.py
QPrism/Audio/helpers/to_mono_wav.py
QPrism/Audio/helpers/waveform.py
QPrism/Sensor/APD.py
QPrism/Sensor/DQM.py
QPrism/Sensor/IRLR.py
QPrism/Sensor/MDR.py
QPrism/Sensor/RLC.py
QPrism/Sensor/SCR.py
QPrism/Sensor/SNR.py
QPrism/Sensor/SRC.py
QPrism/Sensor/VDR.py
QPrism/Sensor/VRC.py
QPrism/Sensor/WASH_MDR_analysis.py
QPrism/Sensor/__init__.py
QPrism/Sensor/data_processing.py
QPrism/Sensor/load_data.py
QPrism/Sensor/pipeline_functions/__init__,py
QPrism/Sensor/pipeline_functions/activity_classifcation.py
QPrism/Sensor/pipeline_functions/outlier_detection.py
QPrism/Sensor/pipeline_functions/preprocessing.py
QPrism/Sensor/pipeline_functions/signal_to_noise.py
QPrism/Sensor/pipeline_functions/single_function_DQMs.py
QPrism/Video/DQM.py
QPrism/Video/__init__.py
QPrism/Video/artifacts.py
QPrism/Video/bit_rate.py
QPrism/Video/brightness.py
QPrism/Video/creation_time.py
QPrism/Video/frame_rate.py
QPrism/Video/object_detection.py
QPrism/Video/video_format.py
QPrism/Video/video_length.py
QPrism/Video/video_resolution.py
QPrism/Video/helpers/download.py
QPrism/Video/helpers/extract_audios.py
QPrism/Video/helpers/video_paths.py
qprism-0.4.0.dist-info/METADATA
qprism-0.4.0.dist-info/WHEEL
qprism-0.4.0.dist-info/licenses/LICENSE
qprism-0.4.0.dist-info/RECORD
