Metadata-Version: 2.1
Name: QPrism
Version: 0.4.0
Summary: A data quality assessment package
Project-URL: homepage, https://github.com/aid4mh/QPrism
Project-URL: documentation, https://qprism.readthedocs.io/en/latest/index.html
Project-URL: repository, https://github.com/aid4mh/QPrism
Author: Ramzi Halabi, Zixiong Lin, Rahavi Selvarajan, Jana Kabrit, Abhishek Pratap
License: MIT License
License-File: LICENSE
Keywords: QPrism,audio,quality assessment,sensor,video
Classifier: License :: OSI Approved :: MIT License
Classifier: Operating System :: OS Independent
Classifier: Programming Language :: Python :: 3
Requires-Python: >=3.7
Requires-Dist: combo==0.1.3
Requires-Dist: imageio==2.21.1
Requires-Dist: moviepy==1.0.3
Requires-Dist: numpy>=1.17.3
Requires-Dist: opencv-python==4.5.3.56
Requires-Dist: pandas==1.2.4
Requires-Dist: pillow==9.0.1
Requires-Dist: pydub==0.25.1
Requires-Dist: pyod==1.0.1
Requires-Dist: scipy==1.7.3
Requires-Dist: tensorflow-hub==0.10.0
Requires-Dist: tensorflow==2.9.1
Requires-Dist: torch==1.12.0
